pybrat/__init__.py
pybrat/parser.py
pybrat/py.typed
pybrat/utils.py
pybrat-0.1.7.dist-info/METADATA
pybrat-0.1.7.dist-info/WHEEL
pybrat-0.1.7.dist-info/RECORD
