Metadata-Version: 2.1
Name: pybrat
Version: 0.1.7
Summary: Parser for brat rapid annotation tool (Brat)
Author: Yevgnen Koh
Author-email: wherejoystarts@gmail.com
Requires-Python: >=3.8,<4.0
Classifier: Programming Language :: Python :: 3
Classifier: Programming Language :: Python :: 3.8
Classifier: Programming Language :: Python :: 3.9
Classifier: Programming Language :: Python :: 3.10
Classifier: Programming Language :: Python :: 3.11
